{
  "sjs2": {
    "typography": {
      "large": {
        "value": {
          "fontFamily": "{sjs2.typography.font-family.text}",
          "fontWeight": "{sjs2.typography.font-weight.basic}",
          "fontSize": "{sjs2.typography.font-size.large}",
          "lineHeight": "{sjs2.typography.line-height.large}"
        },
        "type": "typography"
      },
      "large-strong": {
        "value": {
          "fontFamily": "{sjs2.typography.font-family.text}",
          "fontWeight": "{sjs2.typography.font-weight.strong}",
          "fontSize": "{sjs2.typography.font-size.large}",
          "lineHeight": "{sjs2.typography.line-height.large}"
        },
        "type": "typography"
      },
      "medium": {
        "value": {
          "fontFamily": "{sjs2.typography.font-family.text}",
          "fontWeight": "{sjs2.typography.font-weight.basic}",
          "fontSize": "{sjs2.typography.font-size.medium}",
          "lineHeight": "{sjs2.typography.line-height.medium}"
        },
        "type": "typography"
      },
      "medium-strong": {
        "value": {
          "fontFamily": "{sjs2.typography.font-family.text}",
          "fontWeight": "{sjs2.typography.font-weight.strong}",
          "fontSize": "{sjs2.typography.font-size.medium}",
          "lineHeight": "{sjs2.typography.line-height.medium}"
        },
        "type": "typography"
      },
      "default": {
        "value": {
          "fontFamily": "{sjs2.typography.font-family.text}",
          "fontWeight": "{sjs2.typography.font-weight.basic}",
          "fontSize": "{sjs2.typography.font-size.default}",
          "lineHeight": "{sjs2.typography.line-height.default}"
        },
        "type": "typography"
      },
      "default-strong": {
        "value": {
          "fontFamily": "{sjs2.typography.font-family.text}",
          "fontWeight": "{sjs2.typography.font-weight.strong}",
          "fontSize": "{sjs2.typography.font-size.default}",
          "lineHeight": "{sjs2.typography.line-height.default}"
        },
        "type": "typography"
      },
      "small": {
        "value": {
          "fontFamily": "{sjs2.typography.font-family.text}",
          "fontWeight": "{sjs2.typography.font-weight.basic}",
          "fontSize": "{sjs2.typography.font-size.small}",
          "lineHeight": "{sjs2.typography.line-height.small}"
        },
        "type": "typography"
      },
      "small-strong": {
        "value": {
          "fontFamily": "{sjs2.typography.font-family.text}",
          "fontWeight": "{sjs2.typography.font-weight.strong}",
          "fontSize": "{sjs2.typography.font-size.small}",
          "lineHeight": "{sjs2.typography.line-height.small}"
        },
        "type": "typography"
      },
      "default-code": {
        "value": {
          "fontFamily": "{sjs2.typography.font-family.code}",
          "fontWeight": "{sjs2.typography.font-weight.basic}",
          "fontSize": "{sjs2.typography.font-size.default}",
          "lineHeight": "{sjs2.typography.line-height.default}"
        },
        "type": "typography"
      },
      "component": {
        "input": {
          "text": {
            "value": {
              "fontFamily": "{sjs2.typography.font-family.component.editor.text}",
              "fontWeight": "{sjs2.typography.font-weight.component.editor.text}",
              "fontSize": "{sjs2.typography.font-size.component.editor.text}",
              "lineHeight": "{sjs2.typography.line-height.component.editor.text}"
            },
            "type": "typography"
          }
        },
        "question": {
          "title": {
            "value": {
              "fontFamily": "{sjs2.typography.font-family.component.question.title}",
              "fontWeight": "{sjs2.typography.font-weight.component.question.title}",
              "fontSize": "{sjs2.typography.font-size.component.question.title}",
              "lineHeight": "{sjs2.typography.line-height.component.question.title}"
            },
            "type": "typography"
          },
          "description": {
            "value": {
              "fontFamily": "{sjs2.typography.font-family.component.question.description}",
              "fontWeight": "{sjs2.typography.font-weight.component.question.description}",
              "fontSize": "{sjs2.typography.font-size.component.question.description}",
              "lineHeight": "{sjs2.typography.line-height.component.question.description}"
            },
            "type": "typography"
          }
        },
        "page": {
          "title": {
            "value": {
              "fontFamily": "{sjs2.typography.font-family.component.page.title}",
              "fontWeight": "{sjs2.typography.font-weight.component.page.title}",
              "fontSize": "{sjs2.typography.font-size.component.page.title}",
              "lineHeight": "{sjs2.typography.line-height.component.page.title}"
            },
            "type": "typography"
          },
          "description": {
            "value": {
              "fontFamily": "{sjs2.typography.font-family.component.page.description}",
              "fontWeight": "{sjs2.typography.font-weight.component.page.description}",
              "fontSize": "{sjs2.typography.font-size.component.page.description}",
              "lineHeight": "{sjs2.typography.line-height.component.page.description}"
            },
            "type": "typography"
          }
        },
        "header": {
          "title": {
            "value": {
              "fontFamily": "{sjs2.typography.font-family.component.header.title}",
              "fontWeight": "{sjs2.typography.font-weight.component.header.title}",
              "fontSize": "{sjs2.typography.font-size.component.header.title}",
              "lineHeight": "{sjs2.typography.line-height.component.header.title}"
            },
            "type": "typography"
          },
          "description": {
            "value": {
              "fontFamily": "{sjs2.typography.font-family.text}",
              "fontWeight": "{sjs2.typography.font-weight.basic}",
              "fontSize": "{sjs2.typography.font-size.default}",
              "lineHeight": "{sjs2.typography.line-height.default}"
            },
            "type": "typography"
          }
        }
      },
      "font-family": {
        "text": {
          "value": "Open Sans",
          "type": "fontFamilies"
        },
        "code": {
          "value": "DM Mono",
          "type": "fontFamilies"
        },
        "component": {
          "editor": {
            "text": {
              "value": "Open Sans",
              "type": "fontFamilies"
            }
          },
          "question": {
            "title": {
              "value": "Open Sans",
              "type": "fontFamilies"
            },
            "description": {
              "value": "Open Sans",
              "type": "fontFamilies"
            }
          },
          "page": {
            "title": {
              "value": "Open Sans",
              "type": "fontFamilies"
            },
            "description": {
              "value": "Open Sans",
              "type": "fontFamilies"
            }
          },
          "header": {
            "title": {
              "value": "Open Sans",
              "type": "fontFamilies"
            },
            "description": {
              "value": "Open Sans",
              "type": "fontFamilies"
            }
          }
        }
      },
      "font-size": {
        "small": {
          "value": "{sjs2.font-size.x150}",
          "type": "fontSizes"
        },
        "default": {
          "value": "{sjs2.font-size.x200}",
          "type": "fontSizes"
        },
        "medium": {
          "value": "{sjs2.font-size.x300}",
          "type": "fontSizes"
        },
        "large": {
          "value": "{sjs2.font-size.x400}",
          "type": "fontSizes"
        },
        "component": {
          "editor": {
            "text": {
              "value": "{sjs2.font-size.x200}",
              "type": "fontSizes"
            }
          },
          "question": {
            "title": {
              "value": "{sjs2.font-size.x200}",
              "type": "fontSizes"
            },
            "description": {
              "value": "{sjs2.font-size.x200}",
              "type": "fontSizes"
            }
          },
          "page": {
            "title": {
              "value": "{sjs2.font-size.x300}",
              "type": "fontSizes"
            },
            "description": {
              "value": "{sjs2.font-size.x200}",
              "type": "fontSizes"
            }
          },
          "header": {
            "title": {
              "value": "{sjs2.font-size.x400}",
              "type": "fontSizes"
            },
            "description": {
              "value": "{sjs2.font-size.x300}",
              "type": "fontSizes"
            }
          }
        }
      },
      "line-height": {
        "small": {
          "value": "{sjs2.line-height.x200}",
          "type": "lineHeights"
        },
        "default": {
          "value": "{sjs2.line-height.x300}",
          "type": "lineHeights"
        },
        "medium": {
          "value": "{sjs2.line-height.x400}",
          "type": "lineHeights"
        },
        "large": {
          "value": "{sjs2.line-height.x500}",
          "type": "lineHeights"
        },
        "component": {
          "editor": {
            "text": {
              "value": "{sjs2.line-height.x300}",
              "type": "lineHeights"
            }
          },
          "question": {
            "title": {
              "value": "{sjs2.line-height.x300}",
              "type": "lineHeights"
            },
            "description": {
              "value": "{sjs2.line-height.x300}",
              "type": "lineHeights"
            }
          },
          "page": {
            "title": {
              "value": "{sjs2.line-height.x400}",
              "type": "lineHeights"
            },
            "description": {
              "value": "{sjs2.line-height.x300}",
              "type": "lineHeights"
            }
          },
          "header": {
            "title": {
              "value": "{sjs2.line-height.x500}",
              "type": "lineHeights"
            },
            "description": {
              "value": "{sjs2.line-height.x400}",
              "type": "lineHeights"
            }
          }
        }
      },
      "font-weight": {
        "basic": {
          "value": "{sjs2.font-weight.regular}",
          "type": "fontWeights"
        },
        "strong": {
          "value": "{sjs2.font-weight.semibold}",
          "type": "fontWeights"
        },
        "component": {
          "editor": {
            "text": {
              "value": "{sjs2.font-weight.regular}",
              "type": "fontWeights"
            }
          },
          "question": {
            "title": {
              "value": "{sjs2.font-weight.semibold}",
              "type": "fontWeights"
            },
            "description": {
              "value": "{sjs2.font-weight.regular}",
              "type": "fontWeights"
            }
          },
          "page": {
            "title": {
              "value": "{sjs2.font-weight.semibold}",
              "type": "fontWeights"
            },
            "description": {
              "value": "{sjs2.font-weight.regular}",
              "type": "fontWeights"
            }
          },
          "header": {
            "title": {
              "value": "{sjs2.font-weight.semibold}",
              "type": "fontWeights"
            },
            "description": {
              "value": "{sjs2.font-weight.regular}",
              "type": "fontWeights"
            }
          }
        }
      }
    }
  }
}